branchlog/__init__.py
branchlog/__main__.py
branchlog/local_git.py
branchlog-0.1.1.dist-info/METADATA
branchlog-0.1.1.dist-info/WHEEL
branchlog-0.1.1.dist-info/entry_points.txt
branchlog-0.1.1.dist-info/top_level.txt
branchlog-0.1.1.dist-info/RECORD
