Metadata-Version: 2.4
Name: branchlog
Version: 0.1.1
Summary: Track which git branches you've worked on recently.
Author-email: Rahman <your.email@example.com>
License: MIT
Keywords: git,cli,branches,developer-tools
Classifier: Programming Language :: Python :: 3
Classifier: License :: OSI Approved :: MIT License
Classifier: Operating System :: OS Independent
Requires-Python: >=3.7
